certbot_deployer_vsphere/__init__.py
certbot_deployer_vsphere/__main__.py
certbot_deployer_vsphere/meta.py
certbot_deployer_vsphere/_main/__init__.py
certbot_deployer_vsphere/certbot_deployer_vsphere/__init__.py
certbot_deployer_vsphere-0.1.2.data/scripts/certbot_deployer_vsphere
certbot_deployer_vsphere-0.1.2.dist-info/licenses/LICENSE
certbot_deployer_vsphere-0.1.2.dist-info/METADATA
certbot_deployer_vsphere-0.1.2.dist-info/WHEEL
certbot_deployer_vsphere-0.1.2.dist-info/entry_points.txt
certbot_deployer_vsphere-0.1.2.dist-info/top_level.txt
certbot_deployer_vsphere-0.1.2.dist-info/RECORD
