Metadata-Version: 2.4
Name: certbot_deployer_vsphere
Version: 0.1.2
Summary: author = Certbot Deployer plugin for deploying web certificates to VSphere
Home-page: https://github.com/theias/certbot_deployer_vsphere
Author: IAS
Author-email: network@ias.edu
Project-URL: Documentation, https://theias.github.io/certbot_deployer_vsphere/
Project-URL: Bug Tracker, https://github.com/theias/certbot_deployer_vsphere/issues
Project-URL: Source, https://github.com/theias/certbot_deployer_vsphere
Classifier: Programming Language :: Python :: 3
Classifier: License :: OSI Approved :: MIT License
Classifier: Operating System :: OS Independent
Requires-Python: >=3.9
License-File: LICENSE
Requires-Dist: certbot_deployer<3.0.0,>=2.0.3
Requires-Dist: pyOpenSSL<25.0.0,>=24.2.1
Requires-Dist: requests<2.33.0,>=2.32.3
Requires-Dist: vmware_vapi_runtime<3.0.0,>=2.61.2
Requires-Dist: vmware_vcenter<9.0.0.0,>=8.0.3.0
Dynamic: license-file
